MANIFEST.in
README.rst
setup.cfg
setup.py
versioneer.py
surveymonster/__init__.py
surveymonster/_version.py
surveymonster/load_survey.py
surveymonster/survey.py
surveymonster/transformation.py
surveymonster.egg-info/PKG-INFO
surveymonster.egg-info/SOURCES.txt
surveymonster.egg-info/dependency_links.txt
surveymonster.egg-info/requires.txt
surveymonster.egg-info/top_level.txt