Metadata-Version: 1.1
Name: surveymonster
Version: 0.0.0
Summary: UNKNOWN
Home-page: https://github.com/SurveyMonster/SurveyMonster
Author: Shay Palachy
Author-email: shaypal5@gmail.com
License: MIT
Platform: any
Classifier: Development Status :: 1 - Planning
Classifier: License :: OSI Approved :: MIT License
Classifier: Programming Language :: Python
Classifier: Programming Language :: Python :: 3.5
Classifier: Programming Language :: Python :: 3.6
Classifier: Topic :: Software Development :: Libraries
Classifier: Topic :: Software Development :: Libraries :: Python Modules
Classifier: Intended Audience :: Developers
